{
  "accountInfo": {
    "memberId": "MB789456123",
    "memberSince": "2018-03-15",
    "username": "sarah.chen.travel",
    "email": "sarah.chen@email.com",
    "phone": "+1-434-555-0147",
    "eliteStatus": "Platinum Elite",
    "lifetimeNights": 487,
    "currentYearNights": 52,
    "pointsBalance": 284500
  },

  "personalInfo": {
    "firstName": "Sarah",
    "lastName": "Chen",
    "dateOfBirth": "1987-06-22",
    "address": {
      "street": "2847 Woodland Heights",
      "city": "Crozet",
      "state": "Virginia",
      "zipCode": "22932",
      "country": "United States"
    },
    "emergencyContact": {
      "name": "Michael Chen",
      "relationship": "Spouse",
      "phone": "+1-434-555-0148"
    }
  },

  "roomPreferences": {
    "bedType": "King",
    "floorPreference": "High floor",
    "roomLocation": "Away from elevator",
    "viewPreference": "City view",
    "accessibilityNeeds": "None",
    "pillowType": "Memory foam",
    "roomTemperature": 68,
    "minibar": "Empty for personal use",
    "entertainment": "Smart TV logged in",
    "workspace": "Ergonomic chair"
  },

  "diningPreferences": {
    "dietaryRestrictions": {
      "allergies": ["Shellfish"],
      "dietaryChoice": "Pescatarian",
      "medicalDiet": "None"
    },
    "cuisinePreferences": [
      "Italian",
      "Asian",
      "Mediterranean",
      "American"
    ],
    "breakfastStyle": "Continental",
    "diningStyle": "Fine dining",
    "beveragePreferences": {
      "coffee": "Cappuccino, oat milk",
      "tea": "Green tea",
      "alcohol": "White wine, sake"
    },
    "typicalDinnerTime": "19:00"
  },

  "attractionPreferences": {
    "vibe": { "tier": "Premium", "energy": "Relaxed" },
    "group": "Couple",
    "kidFriendly": false,
    "awakeSleep": { "awakeAt": "06:00", "sleepAt": "22:00" },
    "travel": { "mode": "Drive", "maxMinutes": 40 },
    "socialSetting": "Quiet/Private",
    "activitiesHobbies": ["Modern art", "Architecture tours", "Photography walks", "Planetariums", "Scenic viewpoints"],
    "favoriteMusicGenres": ["Jazz", "Classical/Chamber"],
    "wellnessActivity": ["Yoga/Pilates", "Spa/Thermal", "Easy Walks/Scenic"],
    "languages": ["English", "Mandarin"]
  },  

  "servicePreferences": {
    "communication": {
      "primaryLanguage": "English",
      "secondaryLanguage": "Mandarin",
      "contactMethod": "Text/SMS",
      "marketingOptIn": true,
      "doNotDisturbHours": "22:00-07:00"
    },
    "housekeeping": {
      "frequency": "Daily",
      "preferredTime": "Morning (9-11am)",
      "turndownService": true,
      "turndownTime": "20:00"
    },
    "newspaper": "Digital - WSJ, NY Times",
    "wakeUpCall": false
  },

  "wellnessPreferences": {
    "fitness": {
      "preferredWorkoutTime": "06:00",
      "fitnessClasses": ["Yoga", "Pilates"],
      "equipmentFocus": "Cardio",
      "personalTraining": "Interested"
    },
    "spa": {
      "treatmentTypes": ["Massage", "Facial"],
      "pressurePreference": "Medium",
      "aromatherapy": "Lavender",
      "appointmentTime": "Evening"
    }
  },

  "businessPreferences": {
    "invoiceFormat": "Detailed",
    "corporateCode": "TECHCORP2024",
    "companyName": "TechVision Solutions",
    "meetingRoomSetup": "U-shape",
    "businessCenterNeeds": "Printing"
  },

  "loyaltyPreferences": {
    "pointRedemption": "Save for specific goals",
    "redemptionGoal": "5-night luxury resort stay",
    "eliteBenefitPriority": "Suite upgrades",
    "airlinePartner": "United Airlines",
    "carRentalPartner": "Hertz",
    "bonusOfferInterests": ["Spa", "Dining", "Experiences"]
  },

  "transportationPreferences": {
    "airportTransfer": "Private car",
    "transferTiming": 30,
    "specialNeeds": "None",
    "rentalCarCompany": "Hertz",
    "rentalCarType": "Midsize SUV",
    "parkingPreference": "Valet",
    "evCharging": false
  },

  "specialOccasions": {
    "importantDates": [
      {
        "type": "Birthday",
        "date": "06-22",
        "celebrationStyle": "Subtle acknowledgment"
      },
      {
        "type": "Anniversary",
        "date": "09-14",
        "celebrationStyle": "Private"
      }
    ],
    "welcomeAmenity": "Local specialties",
    "musicPreference": "Jazz, Classical",
    "lightingPreference": "Dim",
    "scentPreference": "Fragrance-free"
  },

  "travelCompanions": {
    "frequentCompanions": [
      {
        "name": "Michael Chen",
        "relationship": "Spouse",
        "memberId": "MB789456124"
      }
    ],
    "childrenAges": [],
    "connectingRooms": true,
    "petFriendly": false
  },

  "culturalPreferences": {
    "prayerMat": false,
    "qiblaDirection": false,
    "sabbathObservance": false,
    "culturalAmenities": "None"
  },

  "technologyPreferences": {
    "mobileKey": true,
    "digitalCheckIn": true,
    "appNotifications": ["Promotions", "Stay updates", "Points activity"],
    "smartRoomControls": "Voice-activated",
    "wifiAutoConnect": true,
    "typicalDeviceCount": 3,
    "streamingServices": ["Netflix", "Spotify"]
  },

  "recentStays": [
    {
      "property": "JW Marriott San Francisco",
      "checkIn": "2025-09-15",
      "checkOut": "2025-09-18",
      "roomType": "Deluxe King City View",
      "rating": 5
    },
    {
      "property": "The Ritz-Carlton, Tokyo",
      "checkIn": "2025-07-22",
      "checkOut": "2025-07-27",
      "roomType": "Club Deluxe King",
      "rating": 5
    },
    {
      "property": "Marriott Marquis New York",
      "checkIn": "2025-06-05",
      "checkOut": "2025-06-08",
      "roomType": "Premium King",
      "rating": 4
    }
  ],

  "upcomingReservations": [
    {
      "confirmationNumber": "MR48372019",
      "property": "W Hotel Miami Beach",
      "checkIn": "2025-11-08",
      "checkOut": "2025-11-12",
      "roomType": "Wonderful King Ocean View",
      "specialRequests": "High floor, early check-in if possible"
    }
  ]
}